{
  "project_info": {
    "project_number": "347220399264",
    "project_id": "tictactoe-dade8",
    "storage_bucket": "tictactoe-dade8.appspot.com"
  },
  "client": [
    {
      "client_info": {
        "mobilesdk_app_id": "1:347220399264:android:dac9b2a8eb3445daf425c5",
        "android_client_info": {
          "package_name": "br.edu.ifsp.scl.distributedtictactoe"
        }
      },
      "oauth_client": [],
      "api_key": [
        {
          "current_key": "AIzaSyAocycNLFiNeXISakreuZDRwzSgPFDaEa4"
        }
      ],
      "services": {
        "appinvite_service": {
          "other_platform_oauth_client": []
        }
      }
    }
  ],
  "configuration_version": "1"
}